{"id":"0B962C01919ADD6B63124D31A18A51AC","objFolder":"\/app\/wa\/messages","message":{"_data":{"id":{"fromMe":false,"remote":"120363336441408563@g.us","id":"0B962C01919ADD6B63124D31A18A51AC","participant":"5518991219382@c.us","_serialized":"false_120363336441408563@g.us_0B962C01919ADD6B63124D31A18A51AC_5518991219382@c.us"},"viewed":false,"body":"Pra que \ud83d\ude02\ud83d\ude02","type":"chat","t":1750949810,"notifyName":"Wagner Vilalva","from":"120363336441408563@g.us","to":"556194135508@c.us","author":"5518991219382@c.us","ack":1,"invis":false,"isNewMsg":true,"star":false,"kicNotified":false,"recvFresh":true,"isFromTemplate":false,"thumbnail":"","richPreviewType":0,"pollInvalidated":false,"isSentCagPollCreation":false,"latestEditMsgKey":null,"latestEditSenderTimestampMs":null,"quotedMsg":{"type":"chat","kind":"chat","body":"Oloko \nKkkk\nVou atr\u00e1s de um cachorro"},"quotedStanzaID":"81F66B146E2BF37EB99920ABC0ED13B2","quotedParticipant":"5519999451826@c.us","mentionedJidList":[],"groupMentions":[],"isEventCanceled":false,"eventInvalidated":false,"isVcardOverMmsDocument":false,"hasReaction":false,"ephemeralDuration":86400,"disappearingModeInitiator":"chat","disappearingModeTrigger":"chat_settings","viewMode":"VISIBLE","messageSecret":{"0":17,"1":161,"2":238,"3":75,"4":140,"5":235,"6":173,"7":202,"8":34,"9":175,"10":62,"11":194,"12":247,"13":173,"14":238,"15":115,"16":171,"17":85,"18":189,"19":168,"20":101,"21":75,"22":4,"23":50,"24":224,"25":113,"26":233,"27":168,"28":7,"29":134,"30":163,"31":201},"inviteGrpType":"DEFAULT","productHeaderImageRejected":false,"lastPlaybackProgress":0,"isDynamicReplyButtonsMsg":false,"isCarouselCard":false,"parentMsgId":null,"callSilenceReason":null,"isVideoCall":false,"callDuration":null,"callCreator":null,"callParticipants":null,"isCallLink":null,"callLinkToken":null,"isMdHistoryMsg":false,"stickerSentTs":0,"isAvatar":false,"lastUpdateFromServerTs":0,"invokedBotWid":null,"bizBotType":null,"botResponseTargetId":null,"botPluginType":null,"botPluginReferenceIndex":null,"botPluginSearchProvider":null,"botPluginSearchUrl":null,"botPluginSearchQuery":null,"botPluginMaybeParent":false,"botReelPluginThumbnailCdnUrl":null,"botMessageDisclaimerText":null,"botMsgBodyType":null,"reportingTokenInfo":{"reportingToken":{"0":198,"1":26,"2":218,"3":2,"4":198,"5":127,"6":238,"7":91,"8":77,"9":112,"10":39,"11":59,"12":133,"13":62,"14":33,"15":140},"version":2,"reportingTag":{"0":1,"1":8,"2":181,"3":4,"4":178,"5":100,"6":193,"7":163,"8":142,"9":222,"10":13,"11":96,"12":113,"13":133,"14":99,"15":162,"16":44,"17":102,"18":238,"19":222}},"requiresDirectConnection":null,"bizContentPlaceholderType":null,"hostedBizEncStateMismatch":false,"senderOrRecipientAccountTypeHosted":false,"placeholderCreatedWhenAccountIsHosted":false,"links":[]},"id":{"fromMe":false,"remote":"120363336441408563@g.us","id":"0B962C01919ADD6B63124D31A18A51AC","participant":"5518991219382@c.us","_serialized":"false_120363336441408563@g.us_0B962C01919ADD6B63124D31A18A51AC_5518991219382@c.us"},"ack":1,"hasMedia":false,"body":"Pra que \ud83d\ude02\ud83d\ude02","type":"chat","timestamp":1750949810,"from":"120363336441408563@g.us","to":"556194135508@c.us","author":"5518991219382@c.us","deviceType":"android","forwardingScore":0,"isStatus":false,"isStarred":false,"fromMe":false,"hasQuotedMsg":true,"hasReaction":false,"vCards":[],"mentionedIds":[],"groupMentions":[],"isGif":false,"links":[]},"quotedMessage":{"_data":{"id":{"fromMe":false,"remote":"120363336441408563@g.us","id":"81F66B146E2BF37EB99920ABC0ED13B2","participant":{"server":"c.us","user":"5519999451826","_serialized":"5519999451826@c.us"},"_serialized":"false_120363336441408563@g.us_81F66B146E2BF37EB99920ABC0ED13B2_5519999451826@c.us"},"rowId":1000058822,"viewed":false,"body":"Oloko \nKkkk\nVou atr\u00e1s de um cachorro","type":"chat","t":1750948827,"from":{"server":"g.us","user":"120363336441408563","_serialized":"120363336441408563@g.us"},"to":{"server":"c.us","user":"556194135508","_serialized":"556194135508@c.us"},"author":{"server":"c.us","user":"5519999451826","_serialized":"5519999451826@c.us"},"ack":1,"invis":true,"star":false,"kicNotified":false,"isFromTemplate":false,"thumbnail":"","richPreviewType":0,"pollOptions":[],"pollInvalidated":false,"pollVotesSnapshot":{"pollVotes":[]},"latestEditMsgKey":null,"latestEditSenderTimestampMs":null,"quotedMsg":{"type":"chat","kind":"chat","body":"Quem gosta de osso \u00e9 cachorro \ud83d\ude02\ud83d\ude02\ud83d\ude02","pollOptions":[]},"quotedStanzaID":"F4FFD6C5FE90A7E15F2EFC34CEC395E6","quotedParticipant":{"server":"c.us","user":"5518991219382","_serialized":"5518991219382@c.us"},"mentionedJidList":[],"groupMentions":[],"eventInvalidated":false,"isVcardOverMmsDocument":false,"hasReaction":false,"ephemeralDuration":86400,"disappearingModeInitiator":"chat","disappearingModeTrigger":"chat_settings","viewMode":"VISIBLE","messageSecret":{"0":39,"1":83,"2":39,"3":181,"4":222,"5":18,"6":181,"7":32,"8":198,"9":180,"10":171,"11":154,"12":137,"13":73,"14":140,"15":98,"16":15,"17":167,"18":77,"19":189,"20":156,"21":27,"22":180,"23":222,"24":203,"25":116,"26":23,"27":175,"28":79,"29":31,"30":75,"31":238},"inviteGrpType":"DEFAULT","productHeaderImageRejected":false,"lastPlaybackProgress":0,"isDynamicReplyButtonsMsg":false,"isCarouselCard":false,"parentMsgId":null,"callSilenceReason":null,"isVideoCall":false,"callDuration":null,"callCreator":null,"callParticipants":null,"isCallLink":null,"callLinkToken":null,"isMdHistoryMsg":false,"stickerSentTs":0,"isAvatar":false,"lastUpdateFromServerTs":0,"invokedBotWid":null,"bizBotType":null,"botResponseTargetId":null,"botPluginType":null,"botPluginReferenceIndex":null,"botPluginSearchProvider":null,"botPluginSearchUrl":null,"botPluginSearchQuery":null,"botPluginMaybeParent":false,"botReelPluginThumbnailCdnUrl":null,"botMessageDisclaimerText":null,"botMsgBodyType":null,"requiresDirectConnection":false,"bizContentPlaceholderType":null,"hostedBizEncStateMismatch":false,"senderOrRecipientAccountTypeHosted":false,"placeholderCreatedWhenAccountIsHosted":false,"links":[]},"id":{"fromMe":false,"remote":"120363336441408563@g.us","id":"81F66B146E2BF37EB99920ABC0ED13B2","participant":{"server":"c.us","user":"5519999451826","_serialized":"5519999451826@c.us"},"_serialized":"false_120363336441408563@g.us_81F66B146E2BF37EB99920ABC0ED13B2_5519999451826@c.us"},"ack":1,"hasMedia":false,"body":"Oloko \nKkkk\nVou atr\u00e1s de um cachorro","type":"chat","timestamp":1750948827,"from":"120363336441408563@g.us","to":"556194135508@c.us","author":"5519999451826@c.us","deviceType":"android","forwardingScore":0,"isStatus":false,"isStarred":false,"fromMe":false,"hasQuotedMsg":true,"hasReaction":false,"vCards":[],"mentionedIds":[],"groupMentions":[],"isGif":false,"links":[]},"ack":0,"ack_list":[],"wbot_id":1,"isSend":false,"isDeleteGroup":true}