{"id":"056E25ED54DF7E703903B64BCF6F6097","objFolder":"\/app\/wa\/messages","message":{"_data":{"id":{"fromMe":false,"remote":"120363391611781466@g.us","id":"056E25ED54DF7E703903B64BCF6F6097","participant":"559481442602@c.us","_serialized":"false_120363391611781466@g.us_056E25ED54DF7E703903B64BCF6F6097_559481442602@c.us"},"viewed":false,"body":"https:\/\/k.kwai.com\/r\/rDOZXpCt\ud83e\udd24\ud83d\udd1e","type":"chat","subtype":"url","t":1750820791,"notifyName":"resili\u00eancia","from":"120363391611781466@g.us","to":"556194135508@c.us","author":"559481442602@c.us","ack":1,"invis":false,"isNewMsg":true,"star":false,"kicNotified":false,"recvFresh":true,"isFromTemplate":false,"matchedText":"https:\/\/k.kwai.com\/r\/rDOZXpCt\ud83e\udd24\ud83d\udd1e","thumbnail":"","richPreviewType":0,"rcat":null,"pollInvalidated":false,"isSentCagPollCreation":false,"latestEditMsgKey":null,"latestEditSenderTimestampMs":null,"mentionedJidList":[],"groupMentions":[],"isEventCanceled":false,"eventInvalidated":false,"isVcardOverMmsDocument":false,"hasReaction":false,"ephemeralDuration":86400,"disappearingModeInitiator":"chat","disappearingModeTrigger":"chat_settings","disappearingModeInitiatedByMe":false,"viewMode":"VISIBLE","messageSecret":{"0":168,"1":9,"2":172,"3":196,"4":58,"5":224,"6":25,"7":46,"8":182,"9":128,"10":157,"11":7,"12":122,"13":14,"14":45,"15":218,"16":9,"17":244,"18":83,"19":250,"20":214,"21":138,"22":35,"23":162,"24":168,"25":193,"26":6,"27":238,"28":223,"29":252,"30":132,"31":179},"inviteGrpType":"DEFAULT","productHeaderImageRejected":false,"lastPlaybackProgress":0,"isDynamicReplyButtonsMsg":false,"isCarouselCard":false,"parentMsgId":null,"callSilenceReason":null,"isVideoCall":false,"callDuration":null,"callCreator":null,"callParticipants":null,"isCallLink":null,"callLinkToken":null,"isMdHistoryMsg":false,"stickerSentTs":0,"isAvatar":false,"lastUpdateFromServerTs":0,"invokedBotWid":null,"bizBotType":null,"botResponseTargetId":null,"botPluginType":null,"botPluginReferenceIndex":null,"botPluginSearchProvider":null,"botPluginSearchUrl":null,"botPluginSearchQuery":null,"botPluginMaybeParent":false,"botReelPluginThumbnailCdnUrl":null,"botMessageDisclaimerText":null,"botMsgBodyType":null,"reportingTokenInfo":{"reportingToken":{"0":68,"1":69,"2":223,"3":152,"4":102,"5":189,"6":247,"7":49,"8":98,"9":166,"10":26,"11":190,"12":155,"13":201,"14":66,"15":243},"version":2,"reportingTag":{"0":1,"1":8,"2":61,"3":6,"4":46,"5":122,"6":220,"7":26,"8":251,"9":131,"10":13,"11":206,"12":93,"13":252,"14":187,"15":114,"16":41,"17":10,"18":29,"19":232}},"requiresDirectConnection":null,"bizContentPlaceholderType":null,"hostedBizEncStateMismatch":false,"senderOrRecipientAccountTypeHosted":false,"placeholderCreatedWhenAccountIsHosted":false,"links":[{"link":"https:\/\/k.kwai.com\/r\/rDOZXpCt\ud83e\udd24\ud83d\udd1e","isSuspicious":false}]},"id":{"fromMe":false,"remote":"120363391611781466@g.us","id":"056E25ED54DF7E703903B64BCF6F6097","participant":"559481442602@c.us","_serialized":"false_120363391611781466@g.us_056E25ED54DF7E703903B64BCF6F6097_559481442602@c.us"},"ack":1,"hasMedia":false,"body":"https:\/\/k.kwai.com\/r\/rDOZXpCt\ud83e\udd24\ud83d\udd1e","type":"chat","timestamp":1750820791,"from":"120363391611781466@g.us","to":"556194135508@c.us","author":"559481442602@c.us","deviceType":"android","forwardingScore":0,"isStatus":false,"isStarred":false,"fromMe":false,"hasQuotedMsg":false,"hasReaction":false,"vCards":[],"mentionedIds":[],"groupMentions":[],"isGif":false,"links":[{"link":"https:\/\/k.kwai.com\/r\/rDOZXpCt\ud83e\udd24\ud83d\udd1e","isSuspicious":false}]},"quotedMessage":null,"ack":0,"ack_list":[],"wbot_id":1,"isSend":false,"isDeleteGroup":true}