{"id":"0855919F252A0BBA50342C9DDE6EF75D","objFolder":"\/app\/wa\/messages","message":{"_data":{"id":{"fromMe":false,"remote":"120363391585618254@g.us","id":"0855919F252A0BBA50342C9DDE6EF75D","participant":"553197540723@c.us","_serialized":"false_120363391585618254@g.us_0855919F252A0BBA50342C9DDE6EF75D_553197540723@c.us"},"viewed":false,"body":"*ALUGO VAGA NA SKY+*\n\nCOM TODOS CANAIS LIBERADOS !\n       ABERTOS E FECHADOS \n\n*N\u00c3O \u00c9 ESSA PORCARIA DE IPTV N\u00c3O , \u00c9 APLICATIVO ORIGINAL , COMO NETFLIX , GLOBO PLAY ETC* \n\n     *E POR ISSO N\u00c3O TRAVA* \nQUALIDADE DE SOM E IMAGEM PERFEITO !!! \n\n\ud83d\udcf1 31-9 9754-0723\n\nDISPOSITIVOS COMPAT\u00cdVEIS*\n\ud83d\udcfa SMART TV          \ud83d\udcfa TV BOX\n\ud83d\udcf2 CELULAR            \ud83d\udcf2  TABLET \n\ud83d\udda5\ufe0f COMPUTADOR   \ud83d\udcbb NOTEBOOK\n\ud83d\udcf6 CHROMECAST   \u2705 MI\/FIRE STICK\n\n\ud83d\udce9Link direto\nhttps:\/\/wa.me\/qr\/G2NQS5TWUMLUB1\n\n\n*Obs : AOS ACOSTUMADOS COM IPTV , N\u00c3O LIBERO NEM 1 SEGUNDO DE TESTE , QUEM LIBERA TESTE \u00c9 QUEM VENDE ESSES IPTV , APP ORIGINAL  \u00c9 CARO TEM CUSTO , PAGOU USOU*\n\n         *VALORES*\n       30 DIAS 40,00\n       \n          *Promo\u00e7\u00f5es*\n    4 meses direto 100\n    6 meses direto 150\n 1 ano direto+ brinde 250\n\n\n\ud83d\ude42\ud83d\ude09\nAutoResponder.ai\nAutoResponder.ai\nAutoResponder.ai\nAutoResponder.ai","type":"chat","subtype":"url","t":1750925931,"notifyName":"Jorge Braga \ud83d\udd37\ud83d\udd39\ud83d\udd3a","from":"120363391585618254@g.us","to":"556194135508@c.us","author":"553197540723@c.us","ack":1,"invis":false,"isNewMsg":true,"star":false,"kicNotified":false,"recvFresh":true,"isFromTemplate":false,"matchedText":"https:\/\/wa.me\/qr\/G2NQS5TWUMLUB1","thumbnail":"","richPreviewType":0,"rcat":null,"pollInvalidated":false,"isSentCagPollCreation":false,"latestEditMsgKey":null,"latestEditSenderTimestampMs":null,"mentionedJidList":[],"groupMentions":[],"isEventCanceled":false,"eventInvalidated":false,"isVcardOverMmsDocument":false,"hasReaction":false,"ephemeralDuration":86400,"disappearingModeInitiator":"chat","disappearingModeTrigger":"chat_settings","disappearingModeInitiatedByMe":false,"viewMode":"VISIBLE","messageSecret":{"0":33,"1":235,"2":225,"3":220,"4":227,"5":225,"6":197,"7":63,"8":239,"9":176,"10":81,"11":176,"12":107,"13":79,"14":191,"15":122,"16":91,"17":224,"18":233,"19":99,"20":48,"21":78,"22":205,"23":239,"24":101,"25":233,"26":210,"27":12,"28":176,"29":70,"30":209,"31":23},"inviteGrpType":"DEFAULT","productHeaderImageRejected":false,"lastPlaybackProgress":0,"isDynamicReplyButtonsMsg":false,"isCarouselCard":false,"parentMsgId":null,"callSilenceReason":null,"isVideoCall":false,"callDuration":null,"callCreator":null,"callParticipants":null,"isCallLink":null,"callLinkToken":null,"isMdHistoryMsg":false,"stickerSentTs":0,"isAvatar":false,"lastUpdateFromServerTs":0,"invokedBotWid":null,"bizBotType":null,"botResponseTargetId":null,"botPluginType":null,"botPluginReferenceIndex":null,"botPluginSearchProvider":null,"botPluginSearchUrl":null,"botPluginSearchQuery":null,"botPluginMaybeParent":false,"botReelPluginThumbnailCdnUrl":null,"botMessageDisclaimerText":null,"botMsgBodyType":null,"reportingTokenInfo":{"reportingToken":{"0":182,"1":224,"2":137,"3":179,"4":67,"5":133,"6":116,"7":111,"8":20,"9":254,"10":147,"11":241,"12":153,"13":1,"14":100,"15":145},"version":2,"reportingTag":{"0":1,"1":8,"2":108,"3":39,"4":111,"5":239,"6":236,"7":214,"8":134,"9":99,"10":132,"11":178,"12":89,"13":200,"14":23,"15":242,"16":99,"17":228,"18":87,"19":5}},"requiresDirectConnection":null,"bizContentPlaceholderType":null,"hostedBizEncStateMismatch":false,"senderOrRecipientAccountTypeHosted":false,"placeholderCreatedWhenAccountIsHosted":false,"links":[{"link":"https:\/\/wa.me\/qr\/G2NQS5TWUMLUB1","isSuspicious":false},{"link":"http:\/\/AutoResponder.ai","isSuspicious":false},{"link":"http:\/\/AutoResponder.ai","isSuspicious":false},{"link":"http:\/\/AutoResponder.ai","isSuspicious":false},{"link":"http:\/\/AutoResponder.ai","isSuspicious":false}]},"id":{"fromMe":false,"remote":"120363391585618254@g.us","id":"0855919F252A0BBA50342C9DDE6EF75D","participant":"553197540723@c.us","_serialized":"false_120363391585618254@g.us_0855919F252A0BBA50342C9DDE6EF75D_553197540723@c.us"},"ack":1,"hasMedia":false,"body":"*ALUGO VAGA NA SKY+*\n\nCOM TODOS CANAIS LIBERADOS !\n       ABERTOS E FECHADOS \n\n*N\u00c3O \u00c9 ESSA PORCARIA DE IPTV N\u00c3O , \u00c9 APLICATIVO ORIGINAL , COMO NETFLIX , GLOBO PLAY ETC* \n\n     *E POR ISSO N\u00c3O TRAVA* \nQUALIDADE DE SOM E IMAGEM PERFEITO !!! \n\n\ud83d\udcf1 31-9 9754-0723\n\nDISPOSITIVOS COMPAT\u00cdVEIS*\n\ud83d\udcfa SMART TV          \ud83d\udcfa TV BOX\n\ud83d\udcf2 CELULAR            \ud83d\udcf2  TABLET \n\ud83d\udda5\ufe0f COMPUTADOR   \ud83d\udcbb NOTEBOOK\n\ud83d\udcf6 CHROMECAST   \u2705 MI\/FIRE STICK\n\n\ud83d\udce9Link direto\nhttps:\/\/wa.me\/qr\/G2NQS5TWUMLUB1\n\n\n*Obs : AOS ACOSTUMADOS COM IPTV , N\u00c3O LIBERO NEM 1 SEGUNDO DE TESTE , QUEM LIBERA TESTE \u00c9 QUEM VENDE ESSES IPTV , APP ORIGINAL  \u00c9 CARO TEM CUSTO , PAGOU USOU*\n\n         *VALORES*\n       30 DIAS 40,00\n       \n          *Promo\u00e7\u00f5es*\n    4 meses direto 100\n    6 meses direto 150\n 1 ano direto+ brinde 250\n\n\n\ud83d\ude42\ud83d\ude09\nAutoResponder.ai\nAutoResponder.ai\nAutoResponder.ai\nAutoResponder.ai","type":"chat","timestamp":1750925931,"from":"120363391585618254@g.us","to":"556194135508@c.us","author":"553197540723@c.us","deviceType":"android","forwardingScore":0,"isStatus":false,"isStarred":false,"fromMe":false,"hasQuotedMsg":false,"hasReaction":false,"vCards":[],"mentionedIds":[],"groupMentions":[],"isGif":false,"links":[{"link":"https:\/\/wa.me\/qr\/G2NQS5TWUMLUB1","isSuspicious":false},{"link":"http:\/\/AutoResponder.ai","isSuspicious":false},{"link":"http:\/\/AutoResponder.ai","isSuspicious":false},{"link":"http:\/\/AutoResponder.ai","isSuspicious":false},{"link":"http:\/\/AutoResponder.ai","isSuspicious":false}]},"quotedMessage":null,"ack":0,"ack_list":[],"wbot_id":1,"isSend":false,"isDeleteGroup":true}