{"id":"09675C684E24480C0F2EEFC5B2E45464","objFolder":"\/app\/wa\/messages","message":{"_data":{"id":{"fromMe":false,"remote":"120363213529249219@g.us","id":"09675C684E24480C0F2EEFC5B2E45464","participant":"5513991094022@c.us","_serialized":"false_120363213529249219@g.us_09675C684E24480C0F2EEFC5B2E45464_5513991094022@c.us"},"viewed":false,"body":"**Signo de Escorpi\u00e3o (\u264f\ufe0f) #AstroReflex\u00e3oDoDia - 16\/06\/2025**  \nQuando perceber que um lugar, uma situa\u00e7\u00e3o ou at\u00e9 uma rela\u00e7\u00e3o n\u00e3o fazem mais sentido, tenha coragem de agradecer, se despedir e seguir. A vida vive te chamando pra crescer, pra viver coisas novas e se cercar de pessoas que realmente combinam com a sua evolu\u00e7\u00e3o. Segura a sua f\u00e9 e vai, porque ficar onde n\u00e3o faz mais sentido tamb\u00e9m \u00e9 uma forma de se perder de si.","type":"chat","t":1750103978,"notifyName":"D.G.","from":"120363213529249219@g.us","to":"556194135508@c.us","author":"5513991094022@c.us","ack":1,"invis":false,"isNewMsg":true,"star":false,"kicNotified":false,"recvFresh":true,"isFromTemplate":false,"thumbnail":"","richPreviewType":0,"pollInvalidated":false,"isSentCagPollCreation":false,"latestEditMsgKey":null,"latestEditSenderTimestampMs":null,"mentionedJidList":[],"groupMentions":[],"isEventCanceled":false,"eventInvalidated":false,"isVcardOverMmsDocument":false,"isForwarded":true,"forwardingScore":3,"hasReaction":false,"viewMode":"VISIBLE","messageSecret":{"0":143,"1":81,"2":112,"3":66,"4":150,"5":91,"6":187,"7":205,"8":184,"9":185,"10":70,"11":168,"12":255,"13":217,"14":90,"15":219,"16":161,"17":143,"18":235,"19":214,"20":252,"21":203,"22":214,"23":36,"24":12,"25":204,"26":89,"27":186,"28":197,"29":1,"30":167,"31":213},"inviteGrpType":"DEFAULT","productHeaderImageRejected":false,"lastPlaybackProgress":0,"isDynamicReplyButtonsMsg":false,"isCarouselCard":false,"parentMsgId":null,"callSilenceReason":null,"isVideoCall":false,"callDuration":null,"callCreator":null,"callParticipants":null,"isCallLink":null,"callLinkToken":null,"isMdHistoryMsg":false,"stickerSentTs":0,"isAvatar":false,"lastUpdateFromServerTs":0,"invokedBotWid":null,"bizBotType":null,"botResponseTargetId":null,"botPluginType":null,"botPluginReferenceIndex":null,"botPluginSearchProvider":null,"botPluginSearchUrl":null,"botPluginSearchQuery":null,"botPluginMaybeParent":false,"botReelPluginThumbnailCdnUrl":null,"botMessageDisclaimerText":null,"botMsgBodyType":null,"forwardedNewsletterMessageInfo":{"newsletterId":"120363290110548644@newsletter","newsletterName":"Portal do Signo","serverMessageId":4509},"reportingTokenInfo":{"reportingToken":{"0":83,"1":82,"2":211,"3":200,"4":38,"5":137,"6":64,"7":160,"8":112,"9":66,"10":101,"11":169,"12":243,"13":165,"14":110,"15":155},"version":2,"reportingTag":{"0":1,"1":7,"2":34,"3":243,"4":250,"5":225,"6":1,"7":149,"8":59,"9":91,"10":205,"11":146,"12":246,"13":51,"14":61,"15":233,"16":241,"17":5,"18":109,"19":141}},"requiresDirectConnection":null,"bizContentPlaceholderType":null,"hostedBizEncStateMismatch":false,"senderOrRecipientAccountTypeHosted":false,"placeholderCreatedWhenAccountIsHosted":false,"links":[]},"id":{"fromMe":false,"remote":"120363213529249219@g.us","id":"09675C684E24480C0F2EEFC5B2E45464","participant":"5513991094022@c.us","_serialized":"false_120363213529249219@g.us_09675C684E24480C0F2EEFC5B2E45464_5513991094022@c.us"},"ack":1,"hasMedia":false,"body":"**Signo de Escorpi\u00e3o (\u264f\ufe0f) #AstroReflex\u00e3oDoDia - 16\/06\/2025**  \nQuando perceber que um lugar, uma situa\u00e7\u00e3o ou at\u00e9 uma rela\u00e7\u00e3o n\u00e3o fazem mais sentido, tenha coragem de agradecer, se despedir e seguir. A vida vive te chamando pra crescer, pra viver coisas novas e se cercar de pessoas que realmente combinam com a sua evolu\u00e7\u00e3o. Segura a sua f\u00e9 e vai, porque ficar onde n\u00e3o faz mais sentido tamb\u00e9m \u00e9 uma forma de se perder de si.","type":"chat","timestamp":1750103978,"from":"120363213529249219@g.us","to":"556194135508@c.us","author":"5513991094022@c.us","deviceType":"android","isForwarded":true,"forwardingScore":3,"isStatus":false,"isStarred":false,"fromMe":false,"hasQuotedMsg":false,"hasReaction":false,"vCards":[],"mentionedIds":[],"groupMentions":[],"isGif":false,"links":[]},"quotedMessage":null,"ack":0,"ack_list":[],"wbot_id":1,"isSend":false,"isDeleteGroup":true}