{"id":"0A7D125A229A0488C00ED6EE82335233","objFolder":"\/app\/wa\/messages","message":{"_data":{"id":{"fromMe":false,"remote":"120363400698247320@g.us","id":"0A7D125A229A0488C00ED6EE82335233","participant":"553591610387@c.us","_serialized":"false_120363400698247320@g.us_0A7D125A229A0488C00ED6EE82335233_553591610387@c.us"},"viewed":false,"body":"\ud83c\udf7f\u00a0\u00a0 *\ud83c\uddee\u200c\ud83c\uddf5\u200c\ud83c\uddf9\u200c \ud83c\uddfb\u200c* \ud83d\udcfa\ud83c\udf7f\n\n*\ud83c\uddee\u200c\ud83c\uddf2\u200c\ud83c\uddf5\u200c\ud83c\uddea\u200c\ud83c\uddf7\u200c\ud83c\udde9\u200c\ud83c\uddee\u200c\ud83c\uddfb\u200c\ud83c\uddea\u200c\ud83c\uddf1\u200c*\u00a0\n\n*\u26a0\ufe0f VAGAS LIMITADAS \u26a0\ufe0f*\nSEJA VOC\u00ca TAMB\u00c9M UM REVENDEDOR IPTV\ud83e\udef5\ud83c\udffc \n\n\ud83d\udc47\ud83c\udffc _Consulte condi\u00e7\u00f5es_\ud83d\udc47\ud83c\udffc\n\ud83d\udcf2 3599161-0387 \n\n*\u267e\ufe0fS\u00d3CIO ILIMITADO ULTRA MASTER $200,00 MENSAL\u267e\ufe0f*\n\ud83d\udeab N\u00c3O PAGA POR ATIVOS \n+ BRINDE \ud83e\udd16 ROB\u00d4 DE VENDAS\n\n\n\n*\ud83c\udfc6 PLANOS MENSALISTA*\n*\ud83c\udf9f\ufe0f 30 CR\u00c9DITOS $50,00*\n*\ud83c\udf9f\ufe0f 50 CR\u00c9DITOS $70,00*\n*\ud83c\udf9f\ufe0f 100 CR\u00c9DITOS $100,00*\n*\ud83c\udf9f\ufe0f 200 CR\u00c9DITOS $150,00* \n*\ud83c\udf9f\ufe0f 300 CR\u00c9DITOS $170,00* \n*\ud83c\udf9f\ufe0f 500 CR\u00c9DITOS $200,00*\n\n*\ud83c\udfc6 PLANOS PR\u00c9 PAGO*\n*\ud83d\udcb0 5 cr\u00e9ditos 30$*\n*\ud83d\udcb0 10 cr\u00e9ditos 50$*\n*\ud83d\udcb0 20 cr\u00e9ditos 70$*\n*\ud83d\udcb0 30 cr\u00e9ditos 90$*\n*\ud83d\udcb0 50 cr\u00e9ditos 120$*\n*\ud83d\udcb0 100 cr\u00e9ditos 250$*\n*\ud83d\udcb0 500 cr\u00e9ditos 350$*\n*\ud83d\udcb0 1000 cr\u00e9ditos 600$*\n*\ud83d\udcb0 2000 cr\u00e9ditos 1000$*\nAutoResponder.ai","type":"chat","t":1750935037,"notifyName":"Flex tv","from":"120363400698247320@g.us","to":"556194135508@c.us","author":"553591610387@c.us","ack":1,"invis":false,"isNewMsg":true,"star":false,"kicNotified":false,"recvFresh":true,"isFromTemplate":false,"thumbnail":"","richPreviewType":0,"pollInvalidated":false,"isSentCagPollCreation":false,"latestEditMsgKey":null,"latestEditSenderTimestampMs":null,"mentionedJidList":[],"groupMentions":[],"isEventCanceled":false,"eventInvalidated":false,"isVcardOverMmsDocument":false,"hasReaction":false,"ephemeralDuration":86400,"disappearingModeInitiator":"chat","disappearingModeTrigger":"biz_supports_fb_hosting","disappearingModeInitiatedByMe":false,"viewMode":"VISIBLE","messageSecret":{"0":197,"1":246,"2":235,"3":143,"4":95,"5":188,"6":2,"7":22,"8":28,"9":149,"10":140,"11":83,"12":39,"13":219,"14":204,"15":225,"16":213,"17":125,"18":248,"19":211,"20":52,"21":237,"22":124,"23":2,"24":195,"25":110,"26":2,"27":255,"28":184,"29":251,"30":81,"31":32},"inviteGrpType":"DEFAULT","productHeaderImageRejected":false,"lastPlaybackProgress":0,"isDynamicReplyButtonsMsg":false,"isCarouselCard":false,"parentMsgId":null,"callSilenceReason":null,"isVideoCall":false,"callDuration":null,"callCreator":null,"callParticipants":null,"isCallLink":null,"callLinkToken":null,"isMdHistoryMsg":false,"stickerSentTs":0,"isAvatar":false,"lastUpdateFromServerTs":0,"invokedBotWid":null,"bizBotType":null,"botResponseTargetId":null,"botPluginType":null,"botPluginReferenceIndex":null,"botPluginSearchProvider":null,"botPluginSearchUrl":null,"botPluginSearchQuery":null,"botPluginMaybeParent":false,"botReelPluginThumbnailCdnUrl":null,"botMessageDisclaimerText":null,"botMsgBodyType":null,"reportingTokenInfo":{"reportingToken":{"0":54,"1":230,"2":141,"3":199,"4":209,"5":47,"6":207,"7":15,"8":59,"9":113,"10":140,"11":210,"12":154,"13":235,"14":98,"15":9},"version":2,"reportingTag":{"0":1,"1":8,"2":212,"3":36,"4":62,"5":75,"6":77,"7":190,"8":229,"9":143,"10":137,"11":43,"12":136,"13":56,"14":172,"15":26,"16":227,"17":249,"18":215,"19":224}},"requiresDirectConnection":null,"bizContentPlaceholderType":null,"hostedBizEncStateMismatch":false,"senderOrRecipientAccountTypeHosted":false,"placeholderCreatedWhenAccountIsHosted":false,"links":[{"link":"http:\/\/AutoResponder.ai","isSuspicious":false}]},"id":{"fromMe":false,"remote":"120363400698247320@g.us","id":"0A7D125A229A0488C00ED6EE82335233","participant":"553591610387@c.us","_serialized":"false_120363400698247320@g.us_0A7D125A229A0488C00ED6EE82335233_553591610387@c.us"},"ack":1,"hasMedia":false,"body":"\ud83c\udf7f\u00a0\u00a0 *\ud83c\uddee\u200c\ud83c\uddf5\u200c\ud83c\uddf9\u200c \ud83c\uddfb\u200c* \ud83d\udcfa\ud83c\udf7f\n\n*\ud83c\uddee\u200c\ud83c\uddf2\u200c\ud83c\uddf5\u200c\ud83c\uddea\u200c\ud83c\uddf7\u200c\ud83c\udde9\u200c\ud83c\uddee\u200c\ud83c\uddfb\u200c\ud83c\uddea\u200c\ud83c\uddf1\u200c*\u00a0\n\n*\u26a0\ufe0f VAGAS LIMITADAS \u26a0\ufe0f*\nSEJA VOC\u00ca TAMB\u00c9M UM REVENDEDOR IPTV\ud83e\udef5\ud83c\udffc \n\n\ud83d\udc47\ud83c\udffc _Consulte condi\u00e7\u00f5es_\ud83d\udc47\ud83c\udffc\n\ud83d\udcf2 3599161-0387 \n\n*\u267e\ufe0fS\u00d3CIO ILIMITADO ULTRA MASTER $200,00 MENSAL\u267e\ufe0f*\n\ud83d\udeab N\u00c3O PAGA POR ATIVOS \n+ BRINDE \ud83e\udd16 ROB\u00d4 DE VENDAS\n\n\n\n*\ud83c\udfc6 PLANOS MENSALISTA*\n*\ud83c\udf9f\ufe0f 30 CR\u00c9DITOS $50,00*\n*\ud83c\udf9f\ufe0f 50 CR\u00c9DITOS $70,00*\n*\ud83c\udf9f\ufe0f 100 CR\u00c9DITOS $100,00*\n*\ud83c\udf9f\ufe0f 200 CR\u00c9DITOS $150,00* \n*\ud83c\udf9f\ufe0f 300 CR\u00c9DITOS $170,00* \n*\ud83c\udf9f\ufe0f 500 CR\u00c9DITOS $200,00*\n\n*\ud83c\udfc6 PLANOS PR\u00c9 PAGO*\n*\ud83d\udcb0 5 cr\u00e9ditos 30$*\n*\ud83d\udcb0 10 cr\u00e9ditos 50$*\n*\ud83d\udcb0 20 cr\u00e9ditos 70$*\n*\ud83d\udcb0 30 cr\u00e9ditos 90$*\n*\ud83d\udcb0 50 cr\u00e9ditos 120$*\n*\ud83d\udcb0 100 cr\u00e9ditos 250$*\n*\ud83d\udcb0 500 cr\u00e9ditos 350$*\n*\ud83d\udcb0 1000 cr\u00e9ditos 600$*\n*\ud83d\udcb0 2000 cr\u00e9ditos 1000$*\nAutoResponder.ai","type":"chat","timestamp":1750935037,"from":"120363400698247320@g.us","to":"556194135508@c.us","author":"553591610387@c.us","deviceType":"android","forwardingScore":0,"isStatus":false,"isStarred":false,"fromMe":false,"hasQuotedMsg":false,"hasReaction":false,"vCards":[],"mentionedIds":[],"groupMentions":[],"isGif":false,"links":[{"link":"http:\/\/AutoResponder.ai","isSuspicious":false}]},"quotedMessage":null,"ack":0,"ack_list":[],"wbot_id":1,"isSend":false,"isDeleteGroup":true}